ComStats/__init__.py
ComStats/comstats.py
ComStats-0.2.0.dist-info/LICENSE
ComStats-0.2.0.dist-info/METADATA
ComStats-0.2.0.dist-info/WHEEL
ComStats-0.2.0.dist-info/top_level.txt
ComStats-0.2.0.dist-info/RECORD
