Metadata-Version: 2.1
Name: ComStats
Version: 0.2.0
Summary: Do combinatorial statistics on numpy ndarrays
Home-page: https://pypi.org/project/ComStats/
Author: Data Science Team @ Zappistore
Author-email: datascience@zappistore.com
License: UNKNOWN
Platform: UNKNOWN
Requires-Dist: numpy
Requires-Dist: scipy
